odoo/addons/hr_holidays_calendar_event_privacy/README.rst
odoo/addons/hr_holidays_calendar_event_privacy/__init__.py
odoo/addons/hr_holidays_calendar_event_privacy/__manifest__.py
odoo/addons/hr_holidays_calendar_event_privacy/i18n/hr_holidays_calendar_event_privacy.pot
odoo/addons/hr_holidays_calendar_event_privacy/i18n/it.po
odoo/addons/hr_holidays_calendar_event_privacy/models/__init__.py
odoo/addons/hr_holidays_calendar_event_privacy/models/hr_leave.py
odoo/addons/hr_holidays_calendar_event_privacy/models/hr_leave_type.py
odoo/addons/hr_holidays_calendar_event_privacy/readme/CONFIGURATION.rst
odoo/addons/hr_holidays_calendar_event_privacy/readme/CONTRIBUTORS.rst
odoo/addons/hr_holidays_calendar_event_privacy/readme/DESCRIPTION.rst
odoo/addons/hr_holidays_calendar_event_privacy/static/description/icon.png
odoo/addons/hr_holidays_calendar_event_privacy/static/description/index.html
odoo/addons/hr_holidays_calendar_event_privacy/tests/__init__.py
odoo/addons/hr_holidays_calendar_event_privacy/tests/test_hr_leave_calendar_event.py
odoo/addons/hr_holidays_calendar_event_privacy/views/hr_leave_type.xml
odoo_addon_hr_holidays_calendar_event_privacy-15.0.1.0.2.dist-info/METADATA
odoo_addon_hr_holidays_calendar_event_privacy-15.0.1.0.2.dist-info/WHEEL
odoo_addon_hr_holidays_calendar_event_privacy-15.0.1.0.2.dist-info/top_level.txt
odoo_addon_hr_holidays_calendar_event_privacy-15.0.1.0.2.dist-info/RECORD
