Metadata-Version: 2.1
Name: odoo-addon-hr_holidays_calendar_event_privacy
Version: 15.0.1.0.2
Summary: Define privacy level of calendar events from Time off requests
Home-page: https://github.com/OCA/hr-holidays
Author: Camptocamp, Odoo Community Association (OCA)
Author-email: support@odoo-community.org
License: AGPL-3
Classifier: Programming Language :: Python
Classifier: Framework :: Odoo
Classifier: Framework :: Odoo :: 15.0
Classifier: License :: OSI Approved :: GNU Affero General Public License v3
Classifier: Development Status :: 3 - Alpha
Requires-Python: >=3.8
Requires-Dist: odoo<15.1dev,>=15.0a
